Metadata-Version: 2.4
Name: llama-index-embeddings-elasticsearch
Version: 0.4.1
Summary: llama-index embeddings elasticsearch integration
Author-email: Your Name <you@example.com>
License-Expression: MIT
License-File: LICENSE
Requires-Python: <4.0,>=3.9
Requires-Dist: elasticsearch<9,>=8.12.0
Requires-Dist: llama-index-core<0.15,>=0.13.0
